baseline/__init__.py
baseline/drqa/__init__.py
baseline/drqa/retriever/__init__.py
baseline/drqa/retriever/doc_db.py
baseline/drqa/retriever/simple.py
baseline/drqa/retriever/tfidf_doc_ranker.py
baseline/drqa/retriever/utils.py
baseline/drqa/tokenizers/__init__.py
baseline/drqa/tokenizers/corenlp_tokenizer.py
baseline/drqa/tokenizers/regexp_tokenizer.py
baseline/drqa/tokenizers/simple_tokenizer.py
baseline/drqa/tokenizers/spacy_tokenizer.py
baseline/drqa/tokenizers/tokenizer.py
baseline/drqascripts/__init__.py
baseline/drqascripts/build_tfidf.py
baseline/drqascripts/build_tfidf_lines.py
baseline/predictor/__init__.py
baseline/predictor/evaluate_verdict_predictor.py
baseline/predictor/train_verdict_predictor.py
baseline/retriever/__init__.py
baseline/retriever/build_db.py
baseline/retriever/build_tfidf.py
baseline/retriever/combine_retrieval.py
baseline/retriever/document_entity_tfidf_ir.py
baseline/retriever/eval_combined_retriever.py
baseline/retriever/eval_doc_retriever.py
baseline/retriever/eval_sentence_retriever.py
baseline/retriever/eval_tab_retriever.py
baseline/retriever/predict_cells_from_table.py
baseline/retriever/sentence_tfidf_drqa.py
baseline/retriever/table_tfidf_drqa.py
baseline/retriever/train_cell_evidence_retriever.py
database/__init__.py
database/create_wiki_db.py
database/feverous_db.py
database/utils.py
examples/__init__.py
examples/read_context.py
examples/read_lists.py
examples/read_tables.py
feverous/__init__.py
feverous/baseline/__init__.py
feverous/baseline/drqa/__init__.py
feverous/baseline/drqa/retriever/__init__.py
feverous/baseline/drqa/retriever/doc_db.py
feverous/baseline/drqa/retriever/simple.py
feverous/baseline/drqa/retriever/tfidf_doc_ranker.py
feverous/baseline/drqa/retriever/utils.py
feverous/baseline/drqa/tokenizers/__init__.py
feverous/baseline/drqa/tokenizers/corenlp_tokenizer.py
feverous/baseline/drqa/tokenizers/regexp_tokenizer.py
feverous/baseline/drqa/tokenizers/simple_tokenizer.py
feverous-0.0.3.dist-info/LICENSE
feverous-0.0.3.dist-info/METADATA
feverous-0.0.3.dist-info/WHEEL
feverous-0.0.3.dist-info/top_level.txt
feverous-0.0.3.dist-info/RECORD
