Metadata-Version: 2.1
Name: feverous
Version: 0.0.3
Summary: Repository for Fact Extraction and VERification Over Unstructured and Structured information (FEVEROUS), used for the FEVER Workshop Shared Task at EMNLP2021.
Home-page: https://github.com/Raldir/FEVEROUS
Author: Rami Aly
Author-email: rmya2@cam.ac.uk
License: MIT
Platform: UNKNOWN
Requires-Python: >=3.6
Requires-Dist: regex (==2020.10.23)
Requires-Dist: numpy (==1.19.1)
Requires-Dist: transformers (==4.1.1)
Requires-Dist: scipy (==1.5.4)
Requires-Dist: clean-text (==0.4.0)
Requires-Dist: pexpect (==4.8.0)
Requires-Dist: spacy (==2.3.2)
Requires-Dist: sklearn
Requires-Dist: jsonlines (==2.0.0)
Requires-Dist: tqdm (==4.46.0)
